{"mape": 0.43805518195790494, "mape_std": 0.11614837973886931, "timestamp": 1752589564, "checkpoint_dir_name": null, "done": false, "training_iteration": 1, "trial_id": "37439_00055", "date": "2025-07-15_15-26-04", "time_this_iter_s": 1.8763542175292969, "time_total_s": 1.8763542175292969, "pid": 211926, "hostname": "genius", "node_ip": "192.168.1.88", "config": {"changepoint_prior_scale": 0.016173269977436504, "seasonality_prior_scale": 1.7678767954307901, "holidays_prior_scale": 43.277347544148974, "seasonality_mode": "additive"}, "time_since_restore": 1.8763542175292969, "iterations_since_restore": 1}
