{"mape": 1.1503413303950065, "mape_std": 0.8632297493235243, "timestamp": 1752590164, "checkpoint_dir_name": null, "done": false, "training_iteration": 1, "trial_id": "37439_00270", "date": "2025-07-15_15-36-04", "time_this_iter_s": 1.998781681060791, "time_total_s": 1.998781681060791, "pid": 234461, "hostname": "genius", "node_ip": "192.168.1.88", "config": {"changepoint_prior_scale": 0.00852860864378184, "seasonality_prior_scale": 8.59572010942883, "holidays_prior_scale": 32.75047800210075, "seasonality_mode": "multiplicative"}, "time_since_restore": 1.998781681060791, "iterations_since_restore": 1}
