{"mape": 0.7066173328417412, "mape_std": 0.28042495359190056, "timestamp": 1752590126, "checkpoint_dir_name": null, "done": false, "training_iteration": 1, "trial_id": "37439_00254", "date": "2025-07-15_15-35-26", "time_this_iter_s": 1.5243988037109375, "time_total_s": 1.5243988037109375, "pid": 232801, "hostname": "genius", "node_ip": "192.168.1.88", "config": {"changepoint_prior_scale": 0.49225130961559266, "seasonality_prior_scale": 1.706808266613938, "holidays_prior_scale": 2.35531953589818, "seasonality_mode": "additive"}, "time_since_restore": 1.5243988037109375, "iterations_since_restore": 1}
