{"mape": 0.04650023125047357, "mape_std": 0.01299329218853187, "timestamp": 1752590431, "checkpoint_dir_name": null, "done": false, "training_iteration": 1, "trial_id": "3c939_00063", "date": "2025-07-15_15-40-31", "time_this_iter_s": 1.6543219089508057, "time_total_s": 1.6543219089508057, "pid": 244291, "hostname": "genius", "node_ip": "192.168.1.88", "config": {"changepoint_prior_scale": 0.003103563526343059, "seasonality_prior_scale": 1.9362046605869436, "holidays_prior_scale": 23.05059410873552, "seasonality_mode": "additive"}, "time_since_restore": 1.6543219089508057, "iterations_since_restore": 1}
