{"mape": 0.2145781968688357, "mape_std": 0.03147538640460402, "timestamp": 1752591712, "checkpoint_dir_name": null, "done": false, "training_iteration": 1, "trial_id": "1f0c6b57", "date": "2025-07-15_16-01-52", "time_this_iter_s": 1.2635772228240967, "time_total_s": 1.2635772228240967, "pid": 281480, "hostname": "genius", "node_ip": "192.168.1.88", "config": {"changepoint_prior_scale": 0.012424005112980599, "seasonality_prior_scale": 4.319470705040746, "holidays_prior_scale": 16.417032153355287, "seasonality_mode": "multiplicative"}, "time_since_restore": 1.2635772228240967, "iterations_since_restore": 1}
