{"mape": 0.11982628953469426, "mape_std": 0.018265243693892746, "timestamp": 1752593227, "checkpoint_dir_name": null, "done": false, "training_iteration": 1, "trial_id": "dbfb4279", "date": "2025-07-15_16-27-07", "time_this_iter_s": 1.0949556827545166, "time_total_s": 1.0949556827545166, "pid": 321234, "hostname": "genius", "node_ip": "192.168.1.88", "config": {"changepoint_prior_scale": 0.015409412366258009, "seasonality_prior_scale": 18.347288265830777, "holidays_prior_scale": 1.6954300574977206, "seasonality_mode": "multiplicative"}, "time_since_restore": 1.0949556827545166, "iterations_since_restore": 1}
