{"mape": 0.07662568156710432, "mape_std": 0.02797103284634329, "timestamp": 1752593411, "checkpoint_dir_name": null, "done": false, "training_iteration": 1, "trial_id": "6ad88358", "date": "2025-07-15_16-30-11", "time_this_iter_s": 0.7398796081542969, "time_total_s": 0.7398796081542969, "pid": 323890, "hostname": "genius", "node_ip": "192.168.1.88", "config": {"changepoint_prior_scale": 0.09925180142984615, "seasonality_prior_scale": 11.880449538228168, "holidays_prior_scale": 5.92106969171848, "seasonality_mode": "multiplicative"}, "time_since_restore": 0.7398796081542969, "iterations_since_restore": 1}
