{"mape": 0.041799283868949426, "mape_std": 0.013223352067604197, "timestamp": 1752597786, "checkpoint_dir_name": null, "done": false, "training_iteration": 1, "trial_id": "2c35cb22", "date": "2025-07-15_17-43-06", "time_this_iter_s": 0.7818777561187744, "time_total_s": 0.7818777561187744, "pid": 343115, "hostname": "genius", "node_ip": "192.168.1.88", "config": {"changepoint_prior_scale": 0.0014301022534256756, "seasonality_prior_scale": 5.749637849922306, "holidays_prior_scale": 20.06855018351485, "seasonality_mode": "multiplicative"}, "time_since_restore": 0.7818777561187744, "iterations_since_restore": 1}
