{"mape": 6.151983539787102, "mape_std": 4.983273474827391, "timestamp": 1752591867, "checkpoint_dir_name": null, "done": false, "training_iteration": 1, "trial_id": "e030967a", "date": "2025-07-15_16-04-27", "time_this_iter_s": 1.8875148296356201, "time_total_s": 1.8875148296356201, "pid": 287048, "hostname": "genius", "node_ip": "192.168.1.88", "config": {"changepoint_prior_scale": 0.008636790082074446, "seasonality_prior_scale": 35.64659499532616, "holidays_prior_scale": 2.9036298724902414, "seasonality_mode": "multiplicative"}, "time_since_restore": 1.8875148296356201, "iterations_since_restore": 1}
