{"mape": 0.45803191016139816, "mape_std": 0.1771549006892718, "timestamp": 1752590073, "checkpoint_dir_name": null, "done": false, "training_iteration": 1, "trial_id": "37439_00235", "date": "2025-07-15_15-34-33", "time_this_iter_s": 1.4123601913452148, "time_total_s": 1.4123601913452148, "pid": 230791, "hostname": "genius", "node_ip": "192.168.1.88", "config": {"changepoint_prior_scale": 0.36194267682266684, "seasonality_prior_scale": 2.3883589901807185, "holidays_prior_scale": 1.5091166640543732, "seasonality_mode": "multiplicative"}, "time_since_restore": 1.4123601913452148, "iterations_since_restore": 1}
