{"mape": 0.33019407926207733, "mape_std": 0.05753365626503603, "timestamp": 1752591607, "checkpoint_dir_name": null, "done": false, "training_iteration": 1, "trial_id": "9872a84c", "date": "2025-07-15_16-00-07", "time_this_iter_s": 1.3327984809875488, "time_total_s": 1.3327984809875488, "pid": 277644, "hostname": "genius", "node_ip": "192.168.1.88", "config": {"changepoint_prior_scale": 0.007800970133819222, "seasonality_prior_scale": 1.996445846036124, "holidays_prior_scale": 1.4631893627906025, "seasonality_mode": "multiplicative"}, "time_since_restore": 1.3327984809875488, "iterations_since_restore": 1}
