{"mape": 0.16346795051167246, "mape_std": 0.04265268528788911, "timestamp": 1752600415, "checkpoint_dir_name": null, "done": false, "training_iteration": 1, "trial_id": "1059b8ab", "date": "2025-07-15_18-26-55", "time_this_iter_s": 0.8561491966247559, "time_total_s": 0.8561491966247559, "pid": 353624, "hostname": "genius", "node_ip": "192.168.1.88", "config": {"changepoint_prior_scale": 0.01680882561160477, "seasonality_prior_scale": 11.996795738227759, "holidays_prior_scale": 3.4538347496853703, "seasonality_mode": "multiplicative"}, "time_since_restore": 0.8561491966247559, "iterations_since_restore": 1}
