{"mape": 2.7036231754795343, "mape_std": 1.8550526124233573, "timestamp": 1752589980, "checkpoint_dir_name": null, "done": false, "training_iteration": 1, "trial_id": "37439_00198", "date": "2025-07-15_15-33-00", "time_this_iter_s": 1.9537367820739746, "time_total_s": 1.9537367820739746, "pid": 226888, "hostname": "genius", "node_ip": "192.168.1.88", "config": {"changepoint_prior_scale": 0.00334087095330046, "seasonality_prior_scale": 6.283749876666518, "holidays_prior_scale": 1.8499933876099486, "seasonality_mode": "additive"}, "time_since_restore": 1.9537367820739746, "iterations_since_restore": 1}
