{"mape": 0.03807196084076831, "mape_std": 0.01235351833654375, "timestamp": 1752592291, "checkpoint_dir_name": null, "done": false, "training_iteration": 1, "trial_id": "bff9892f", "date": "2025-07-15_16-11-31", "time_this_iter_s": 3.1087961196899414, "time_total_s": 3.1087961196899414, "pid": 302325, "hostname": "genius", "node_ip": "192.168.1.88", "config": {"changepoint_prior_scale": 0.0194746285821864, "seasonality_prior_scale": 33.22157520514204, "holidays_prior_scale": 1.5182540531958846, "seasonality_mode": "additive"}, "time_since_restore": 3.1087961196899414, "iterations_since_restore": 1}
